README.md
setup.py
lode_runner/__init__.py
lode_runner/core.py
lode_runner/exceptions.py
lode_runner/lode_merge_xunit.py
lode_runner.egg-info/PKG-INFO
lode_runner.egg-info/SOURCES.txt
lode_runner.egg-info/dependency_links.txt
lode_runner.egg-info/entry_points.txt
lode_runner.egg-info/not-zip-safe
lode_runner.egg-info/requires.txt
lode_runner.egg-info/top_level.txt
lode_runner/plugins/__init__.py
lode_runner/plugins/class_skipper.py
lode_runner/plugins/dataprovider.py
lode_runner/plugins/failer.py
lode_runner/plugins/initializer.py
lode_runner/plugins/json_reporter.py
lode_runner/plugins/multiprocess.py
lode_runner/plugins/suppressor.py
lode_runner/plugins/testid.py
lode_runner/plugins/xunit.py