Metadata-Version: 1.1
Name: lode-runner
Version: 0.4.5
Summary: Nosetests runner plugins package
Home-page: https://github.com/2gis/lode_runner
Author: Igor Pavlov
Author-email: nwlunatic@yandex.ru
License: UNKNOWN
Platform: UNKNOWN
Classifier: Operating System :: OS Independent
Classifier: Programming Language :: Python
Classifier: Programming Language :: Python :: 3
Classifier: Topic :: Software Development :: Testing
